main.py
client_analysis/__init__.py
client_analysis/analysis.py
client_analysis_by_podpivas-0.1.dist-info/METADATA
client_analysis_by_podpivas-0.1.dist-info/WHEEL
client_analysis_by_podpivas-0.1.dist-info/entry_points.txt
client_analysis_by_podpivas-0.1.dist-info/top_level.txt
client_analysis_by_podpivas-0.1.dist-info/RECORD
